tbvcfreport/__init__.py
tbvcfreport/dbconn.py
tbvcfreport/report.py
tbvcfreport/tbprofiler.py
tbvcfreport/tbvcfreport.py
tbvcfreport/vcfproc.py
tbvcfreport/templates/base.html
tbvcfreport/templates/drug_resistance_report.html
tbvcfreport/templates/report-layout.html
tbvcfreport-0.1.7.dev20190823.dist-info/LICENSE
tbvcfreport-0.1.7.dev20190823.dist-info/METADATA
tbvcfreport-0.1.7.dev20190823.dist-info/WHEEL
tbvcfreport-0.1.7.dev20190823.dist-info/dependency_links.txt
tbvcfreport-0.1.7.dev20190823.dist-info/entry_points.txt
tbvcfreport-0.1.7.dev20190823.dist-info/top_level.txt
tbvcfreport-0.1.7.dev20190823.dist-info/RECORD
