Metadata-Version: 2.1
Name: tbvcfreport
Version: 0.1.7.dev20190823
Summary: Parses SnpEff generated VCF and generates an HTML report.
Home-page: https://github.com/COMBAT-TB/tbvcfreport
Author: SANBI
Author-email: help@sanbi.ac.za
License: GPLv3
Project-URL: Project, https://combattb.org
Project-URL: Source, https://github.com/COMBAT-TB/tbvcfreport
Project-URL: Tracker, https://github.com/COMBAT-TB/tbvcfreport/issues
Keywords: neo4j,vcf,tuberculosis,h37rv,snpeff
Platform: UNKNOWN
Classifier: License :: OSI Approved :: GNU General Public License v3 (GPLv3)
Classifier: Intended Audience :: Science/Research
Classifier: Programming Language :: Python :: 3.6
Classifier: Programming Language :: Python :: 3.7
Requires-Python: ~=3.6
Requires-Dist: click
Requires-Dist: py2neo
Requires-Dist: jinja2
Requires-Dist: tqdm
Requires-Dist: pyvcf
Requires-Dist: snpit
